pyesaj/__init__.py
pyesaj/request/__init__.py
pyesaj/scraper/__init__.py
pyesaj/scraper/outros/__init__.py
pyesaj/scraper/outros/format.py
pyesaj/scraper/outros/logger.py
pyesaj/scraper/page/__init__.py
pyesaj/scraper/page/cadastro.py
pyesaj/scraper/page/components/__init__.py
pyesaj/scraper/page/components/components.py
pyesaj/scraper/page/intim/__init__.py
pyesaj/scraper/page/intim/consulta.py
pyesaj/scraper/page/intim/define.py
pyesaj/scraper/page/intim/general.py
pyesaj/scraper/page/intim/recebe.py
pyesaj/scraper/page/login.py
pyesaj/scraper/page/processo/__init__.py
pyesaj/scraper/page/processo/consulta.py
pyesaj/scraper/page/processo/registro.py
pyesaj/scraper/params/__init__.py
pyesaj/scraper/params/intim/__init__.py
pyesaj/scraper/params/intim/input.py
pyesaj/scraper/params/intim/output.py
pyesaj/scraper/params/perfil.py
pyesaj/scraper/params/processo/__init__.py
pyesaj/scraper/params/processo/input.py
pyesaj/scraper/pom/__init__.py
pyesaj/scraper/pom/page_object.py
pyesaj/scraper/search/__init__.py
pyesaj/scraper/search/intimacoes.py
pyesaj/scraper/search/processos.py
pyesaj/scraper/webdriver/__init__.py
pyesaj/scraper/webdriver/chrome.py
pyesaj/scraper/webdriver/config.py
pyesaj/scraper/webdriver/firefox.py
pyesaj/scraper/webdriver/gecko.py
pyesaj-1.1.24.dist-info/LICENSE
pyesaj-1.1.24.dist-info/METADATA
pyesaj-1.1.24.dist-info/WHEEL
pyesaj-1.1.24.dist-info/RECORD
