Metadata-Version: 2.3
Name: pyesaj
Version: 1.1.24
Summary: Programa para interagir com o 'Sistema de Automação da Justiça' (e-SAJ), do Tribunal de Justiça do Estado de São Paulo (TJSP)
License: GPL-3.0
Keywords: esaj,tjsp,mpsp
Author: Michel Metran
Author-email: michelmetran@gmail.com
Requires-Python: >=3.10
Classifier: Programming Language :: Python :: 3
Classifier: Operating System :: OS Independent
Classifier: License :: OSI Approved :: GNU General Public License v3 (GPLv3)
Classifier: Natural Language :: Portuguese (Brazilian)
Classifier: Intended Audience :: Developers
Requires-Dist: notebook (>=7.3.3,<8.0.0)
Requires-Dist: openpyxl (>=3.1.5,<4.0.0)
Requires-Dist: pandas (>=2.2.2,<3.0.0)
Requires-Dist: pydantic[email] (>=2.10.6,<3.0.0)
Requires-Dist: python-dotenv (>=1.0.1,<2.0.0)
Requires-Dist: requests (>=2.32.3,<3.0.0)
Requires-Dist: selenium (>=4.30.0,<5.0.0)
Project-URL: Documentation, https://pyESAJ.readthedocs.io
Project-URL: Homepage, https://github.com/michelmetran/pyESAJ
Project-URL: Issues, https://github.com/michelmetran/pyESAJ/issues
Project-URL: Repository, https://github.com/michelmetran/pyESAJ.git
